CHANGES.txt
MANIFEST.in
README.md
setup.cfg
setup.py
por/__init__.py
por.trac.egg-info/PKG-INFO
por.trac.egg-info/SOURCES.txt
por.trac.egg-info/dependency_links.txt
por.trac.egg-info/entry_points.txt
por.trac.egg-info/namespace_packages.txt
por.trac.egg-info/not-zip-safe
por.trac.egg-info/requires.txt
por.trac.egg-info/top_level.txt
por/trac/__init__.py
por/trac/api.py
por/trac/auth_wsgi.py
por/trac/authz.py
por/trac/events.py
por/trac/populate.py