Metadata-Version: 1.0
Name: por.trac
Version: 1.6
Summary: Penelope: Trac integration
Home-page: http://getpenelope.github.com
Author: Penelope Team
Author-email: penelopedev@redturtle.it
License: UNKNOWN
Keywords: web wsgi bfg pylons pyramid
Platform: UNKNOWN
Classifier: Programming Language :: Python
Classifier: Framework :: Pylons
